{
  "compound_id": "DB00530",
  "compound_name": "Erlotinib",
  "compound_percentile": 0.786764705882353,
  "disease_id": "DOID:9352",
  "disease_name": "type 2 diabetes mellitus",
  "disease_percentile": 0.746423927178153,
  "metapath_contribution": {
    "CbGaD": 0.3137857625241674,
    "CbGbCtD": 0.418934915630401,
    "CbGeAlD": 0.0322488786184801,
    "CbGpPWpGaD": 0.09803948514374447,
    "CcSEcCtD": 0.13424372808653565,
    "CrCbGaD": 0.0027472299966712875
  },
  "n_trials": 0.0,
  "prediction": 0.0043559995874337,
  "status": 0,
  "training_prediction": 0.0421786862558152
}