{
  "compound_id": "DB05294",
  "compound_name": "Vandetanib",
  "compound_percentile": 0.801470588235294,
  "disease_id": "DOID:12361",
  "disease_name": "Graves' disease",
  "disease_percentile": 0.688556566970091,
  "metapath_contribution": {
    "CbGeAlD": 0.06910075603120844,
    "CbGpPWpGaD": 0.05583949686109174,
    "CcSEcCtD": 0.010917805505885296,
    "CtDrD": 0.8641419416018146
  },
  "n_trials": 0.0,
  "prediction": 0.00192315954850718,
  "status": 0,
  "training_prediction": 0.00141852001198175
}