{
  "compound_id": "DB08819",
  "compound_name": "Tafluprost",
  "compound_percentile": 0.9558823529411771,
  "disease_id": "DOID:7148",
  "disease_name": "rheumatoid arthritis",
  "disease_percentile": 0.6573472041612479,
  "metapath_contribution": {
    "CbGaD": 0.45410295406906387,
    "CbGbCtD": 0.44965055746007576,
    "CbGdCrCtD": 0.005182429790778149,
    "CbGpPWpGaD": 0.0696436397869684,
    "CcSEcCtD": 0.021420418893113764
  },
  "n_trials": 0.0,
  "prediction": 0.0022323386656224803,
  "status": 0
}