{
  "compound_id": "DB00764",
  "compound_name": "Mometasone",
  "compound_percentile": 0.941176470588235,
  "disease_id": "DOID:3083",
  "disease_name": "chronic obstructive pulmonary disease",
  "disease_percentile": 0.9720416124837451,
  "metapath_contribution": {
    "CbGbCtD": 0.10404655872217533,
    "CbGpPWpGaD": 0.0016695501192758918,
    "CcSEcCtD": 0.048090802846257184,
    "CrCbGaD": 0.00032650715554907207,
    "CrCrCtD": 0.21450298197390913,
    "CrCtD": 0.3013129648576976,
    "CtDrD": 0.33005063432513576
  },
  "n_trials": 0.0,
  "prediction": 0.0154859167522603,
  "status": 0,
  "training_prediction": 0.0731523120874551
}