{
  "compound_id": "DB00394",
  "compound_name": "Beclomethasone",
  "compound_percentile": 0.904411764705882,
  "disease_id": "DOID:2531",
  "disease_name": "hematologic cancer",
  "disease_percentile": 0.905071521456437,
  "metapath_contribution": {
    "CbGaD": 0.11710511451093775,
    "CbGbCtD": 0.19483195811750811,
    "CbGeAlD": 0.0020717706159111863,
    "CbGpPWpGaD": 0.016554232312409423,
    "CcSEcCtD": 0.05817538897819392,
    "CrCbGaD": 0.001589955295473549,
    "CrCrCtD": 0.2588586317890812,
    "CrCtD": 0.3508129483804848
  },
  "n_trials": 2.0,
  "prediction": 0.00927424714522492,
  "status": 0,
  "training_prediction": 0.12437966520968
}