{
  "compound_id": "DB00795",
  "compound_name": "Sulfasalazine",
  "compound_percentile": 0.713235294117647,
  "disease_id": "DOID:4481",
  "disease_name": "allergic rhinitis",
  "disease_percentile": 0.630039011703511,
  "metapath_contribution": {
    "CbGbCtD": 0.8622234104232244,
    "CbGdCrCtD": 0.00532520890294501,
    "CbGeAlD": 0.06282902560249198,
    "CbGpPWpGaD": 0.06962235507133854
  },
  "n_trials": 0.0,
  "prediction": 0.00279840863094866,
  "status": 0,
  "training_prediction": 0.0254463678534339
}