{
  "compound_id": "DB00688",
  "compound_name": "Mycophenolate mofetil",
  "compound_percentile": 0.7058823529411771,
  "disease_id": "DOID:12365",
  "disease_name": "malaria",
  "disease_percentile": 0.533810143042913,
  "metapath_contribution": {
    "CbGbCtD": 0.6060340296999124,
    "CbGeAlD": 0.12397136858134329,
    "CbGpPWpGaD": 0.05988969073455878,
    "CcSEcCtD": 0.21010491098418554
  },
  "n_trials": 0.0,
  "prediction": 0.00216160679930471,
  "status": 0,
  "training_prediction": 0.012490795657133997
}