{
  "compound_id": "DB00316",
  "compound_name": "Acetaminophen",
  "compound_percentile": 0.8308823529411771,
  "disease_id": "DOID:11054",
  "disease_name": "urinary bladder cancer",
  "disease_percentile": 0.951235370611183,
  "metapath_contribution": {
    "CbGaD": 0.5225190478819501,
    "CbGbCtD": 0.21769218339080404,
    "CbGeAlD": 0.057901571298165755,
    "CbGpPWpGaD": 0.11931419868993391,
    "CcSEcCtD": 0.08257299873914624
  },
  "n_trials": 0.0,
  "prediction": 0.0059038639215207795,
  "status": 0
}