{
  "compound_id": "DB01165",
  "compound_name": "Ofloxacin",
  "compound_percentile": 0.529411764705882,
  "disease_id": "DOID:1909",
  "disease_name": "melanoma",
  "disease_percentile": 0.350455136540962,
  "metapath_contribution": {
    "CbGbCtD": 0.7331910232072604,
    "CbGdCrCtD": 0.002800344266932936,
    "CbGpPWpGaD": 0.051081900981488945,
    "CcSEcCtD": 0.21193403349485898,
    "CrCbGaD": 0.0009926980494587407
  },
  "n_trials": 0.0,
  "prediction": 0.00115140765819455,
  "status": 0
}