{
  "compound_id": "DB08907",
  "compound_name": "Canagliflozin",
  "compound_percentile": 0.926470588235294,
  "disease_id": "DOID:263",
  "disease_name": "kidney cancer",
  "disease_percentile": 0.9135240572171651,
  "metapath_contribution": {
    "CbGaD": 0.1660365186467078,
    "CbGbCtD": 0.5003615983159703,
    "CbGeAlD": 0.08248461251687672,
    "CbGpPWpGaD": 0.09637197473533525,
    "CcSEcCtD": 0.15186160921020533,
    "CrCbGaD": 0.0028836865749045587
  },
  "n_trials": 0.0,
  "prediction": 0.00503672561094367,
  "status": 0
}