{
  "compound_id": "DB00683",
  "compound_name": "Midazolam",
  "compound_percentile": 0.5220588235294121,
  "disease_id": "DOID:585",
  "disease_name": "nephrolithiasis",
  "disease_percentile": 0.283485045513654,
  "metapath_contribution": {
    "CbGeAlD": 0.031898465412169424,
    "CbGpPWpGaD": 0.5528443014406044,
    "CcSEcCtD": 0.4145823072992106,
    "CrCbGaD": 0.0006749258480155849
  },
  "n_trials": 0.0,
  "prediction": 0.0012320004732341802,
  "status": 0,
  "training_prediction": 0.000555348229480815
}