{
  "compound_id": "DB00182",
  "compound_name": "Amphetamine",
  "compound_percentile": 0.786764705882353,
  "disease_id": "DOID:10283",
  "disease_name": "prostate cancer",
  "disease_percentile": 0.342652795838752,
  "metapath_contribution": {
    "CbGaD": 0.525553974530727,
    "CbGbCtD": 0.13172627072832716,
    "CbGeAlD": 0.03483203374979755,
    "CbGpPWpGaD": 0.1264507506360125,
    "CcSEcCtD": 0.17700245523623845,
    "CrCbGaD": 0.004434515118897219
  },
  "n_trials": 0.0,
  "prediction": 0.00170708802029101,
  "status": 0
}