{
  "compound_id": "DB00967",
  "compound_name": "Desloratadine",
  "compound_percentile": 0.691176470588235,
  "disease_id": "DOID:11054",
  "disease_name": "urinary bladder cancer",
  "disease_percentile": 0.6326397919375811,
  "metapath_contribution": {
    "CbGbCtD": 0.6247975256873767,
    "CbGeAlD": 0.039616277016337784,
    "CbGpPWpGaD": 0.09608450460527072,
    "CcSEcCtD": 0.23950169269101496
  },
  "n_trials": 0.0,
  "prediction": 0.0019287269042231698,
  "status": 0,
  "training_prediction": 0.004939965004171
}