{
  "compound_id": "DB05294",
  "compound_name": "Vandetanib",
  "compound_percentile": 0.691176470588235,
  "disease_id": "DOID:2841",
  "disease_name": "asthma",
  "disease_percentile": 0.14824447334200302,
  "metapath_contribution": {
    "CbGaD": 0.3922470530364796,
    "CbGbCtD": 0.17632006218538607,
    "CbGdCrCtD": 0.003097425543316434,
    "CbGeAlD": 0.09319679953559197,
    "CbGpPWpGaD": 0.15536794070835647,
    "CcSEcCtD": 0.17570431762926994,
    "CrCbGaD": 0.00406640136159951
  },
  "n_trials": 0.0,
  "prediction": 0.0013460148172047199,
  "status": 0,
  "training_prediction": 0.009125397509252441
}