{
  "compound_id": "DB01223",
  "compound_name": "Aminophylline",
  "compound_percentile": 0.852941176470588,
  "disease_id": "DOID:10283",
  "disease_name": "prostate cancer",
  "disease_percentile": 0.659297789336801,
  "metapath_contribution": {
    "CbGaD": 0.31231970429912975,
    "CbGbCtD": 0.36256857272489357,
    "CbGdCrCtD": 0.0019480849711304758,
    "CbGeAlD": 0.04944854611589526,
    "CbGpPWpGaD": 0.12742131795810413,
    "CcSEcCtD": 0.142756327402181,
    "CrCbGaD": 0.0035374465286657475
  },
  "n_trials": 1.0,
  "prediction": 0.0032003386532005198,
  "status": 0,
  "training_prediction": 0.0223230202742766
}