{
  "compound_id": "DB08881",
  "compound_name": "Vemurafenib",
  "compound_percentile": 0.9191176470588229,
  "disease_id": "DOID:9074",
  "disease_name": "systemic lupus erythematosus",
  "disease_percentile": 0.9096228868660601,
  "metapath_contribution": {
    "CbGaD": 0.10325789507650338,
    "CbGbCtD": 0.23456111694371054,
    "CbGeAlD": 0.014296905882449333,
    "CbGpPWpGaD": 0.04827661877308123,
    "CcSEcCtD": 0.054669835987709775,
    "CiPCiCtD": 0.5444616670217741,
    "CrCbGaD": 0.0004759603147715537
  },
  "n_trials": 0.0,
  "prediction": 0.0054577971023246,
  "status": 0,
  "training_prediction": 0.0260399513262047
}