{
  "compound_id": "DB00530",
  "compound_name": "Erlotinib",
  "compound_percentile": 0.3970588235294121,
  "disease_id": "DOID:13378",
  "disease_name": "Kawasaki disease",
  "disease_percentile": 0.8068920676202859,
  "metapath_contribution": {
    "CbGbCtD": 0.6648704679520472,
    "CbGeAlD": 0.1670280352046864,
    "CbGpPWpGaD": 0.02450335627626145,
    "CcSEcCtD": 0.12028392871896691,
    "CrCbGaD": 0.02331421184803803
  },
  "n_trials": 0.0,
  "prediction": 0.00217705577931842,
  "status": 0,
  "training_prediction": 0.0022288173140293604
}