{
  "compound_id": "DB00938",
  "compound_name": "Salmeterol",
  "compound_percentile": 0.786764705882353,
  "disease_id": "DOID:11612",
  "disease_name": "polycystic ovary syndrome",
  "disease_percentile": 0.7769830949284791,
  "metapath_contribution": {
    "CbGaD": 0.771462917601706,
    "CbGpPWpGaD": 0.09058713808358579,
    "CcSEcCtD": 0.1286758087520899,
    "CrCbGaD": 0.009274135562618309
  },
  "n_trials": 0.0,
  "prediction": 0.00205996143807285,
  "status": 0,
  "training_prediction": 0.0009289907460249641
}