{
  "compound_id": "DB05294",
  "compound_name": "Vandetanib",
  "compound_percentile": 0.720588235294118,
  "disease_id": "DOID:4045",
  "disease_name": "muscle cancer",
  "disease_percentile": 0.477243172951886,
  "metapath_contribution": {
    "CbGaD": 0.4438111666718322,
    "CbGbCtD": 0.28082793367887254,
    "CbGdCrCtD": 0.0034663351453795965,
    "CbGeAlD": 0.08734681801799328,
    "CbGpPWpGaD": 0.1188440300823756,
    "CcSEcCtD": 0.06570371640354682
  },
  "n_trials": 0.0,
  "prediction": 0.00140312499497224,
  "status": 0,
  "training_prediction": 0.00228877260265497
}