{
  "compound_id": "DB00768",
  "compound_name": "Olopatadine",
  "compound_percentile": 0.5367647058823529,
  "disease_id": "DOID:9074",
  "disease_name": "systemic lupus erythematosus",
  "disease_percentile": 0.16970091027308198,
  "metapath_contribution": {
    "CbGbCtD": 0.18605110111404166,
    "CbGeAlD": 0.18485331090531454,
    "CbGpPWpGaD": 0.34999753614089735,
    "CcSEcCtD": 0.2788981348099935,
    "CrCbGaD": 0.00019991702975290238
  },
  "n_trials": 0.0,
  "prediction": 0.00107755786651902,
  "status": 0,
  "training_prediction": 0.00313888121628667
}