{
  "compound_id": "DB04573",
  "compound_name": "Estriol",
  "compound_percentile": 0.691176470588235,
  "disease_id": "DOID:219",
  "disease_name": "colon cancer",
  "disease_percentile": 0.538361508452536,
  "metapath_contribution": {
    "CbGaD": 0.6460235404160579,
    "CbGbCtD": 0.15673304319358536,
    "CbGeAlD": 0.04225535138189332,
    "CbGpPWpGaD": 0.059081582788536584,
    "CcSEcCtD": 0.09369860686527304,
    "CrCbGaD": 0.0022078753546538638
  },
  "n_trials": 0.0,
  "prediction": 0.00164697322832478,
  "status": 0
}