{
  "compound_id": "DB01065",
  "compound_name": "Melatonin",
  "compound_percentile": 0.654411764705882,
  "disease_id": "DOID:11934",
  "disease_name": "head and neck cancer",
  "disease_percentile": 0.841352405721717,
  "metapath_contribution": {
    "CbGaD": 0.5782730550044551,
    "CbGbCtD": 0.10439824408546947,
    "CbGeAlD": 0.11208758612118712,
    "CbGpPWpGaD": 0.14955732729093138,
    "CcSEcCtD": 0.054790499376616064,
    "CrCbGaD": 0.0008932881213407759
  },
  "n_trials": 2.0,
  "prediction": 0.00230519576809437,
  "status": 0
}