{
  "compound_id": "DB08815",
  "compound_name": "Lurasidone",
  "compound_percentile": 0.970588235294118,
  "disease_id": "DOID:9970",
  "disease_name": "obesity",
  "disease_percentile": 0.8868660598179449,
  "metapath_contribution": {
    "CbGaD": 0.3204667830646671,
    "CbGbCtD": 0.3916168192136308,
    "CbGeAlD": 0.03597640304058416,
    "CbGpPWpGaD": 0.10225924589834279,
    "CcSEcCtD": 0.14623175019970455,
    "CrCbGaD": 0.003448998583070635
  },
  "n_trials": 0.0,
  "prediction": 0.00772674732793726,
  "status": 0
}