{
  "compound_id": "DB00651",
  "compound_name": "Dyphylline",
  "compound_percentile": 0.838235294117647,
  "disease_id": "DOID:0050741",
  "disease_name": "alcohol dependence",
  "disease_percentile": 0.296488946684005,
  "metapath_contribution": {
    "CbGeAlD": 0.2885934875659052,
    "CbGpPWpGaD": 0.4397142776628128,
    "CcSEcCtD": 0.2588652160098156,
    "CrCbGaD": 0.012827018761466458
  },
  "n_trials": 0.0,
  "prediction": 0.0015585928138656699,
  "status": 0,
  "training_prediction": 0.0018917833442663198
}