{
  "compound_id": "DB00977",
  "compound_name": "Ethinyl Estradiol",
  "compound_percentile": 0.25,
  "disease_id": "DOID:1115",
  "disease_name": "sarcoma",
  "disease_percentile": 0.0455136540962289,
  "metapath_contribution": {
    "CbGbCtD": 0.7475626092897479,
    "CbGeAlD": 0.054568595982448544,
    "CbGpPWpGaD": 0.07119300831685191,
    "CcSEcCtD": 0.12667578641095165
  },
  "n_trials": 0.0,
  "prediction": 0.000664722351518212,
  "status": 0,
  "training_prediction": 0.0022354203747979103
}