{
  "compound_id": "DB00995",
  "compound_name": "Auranofin",
  "compound_percentile": 0.639705882352941,
  "disease_id": "DOID:1781",
  "disease_name": "thyroid cancer",
  "disease_percentile": 0.933029908972692,
  "metapath_contribution": {
    "CbGbCtD": 0.3096907956979497,
    "CbGeAlD": 0.17729363102662454,
    "CbGpPWpGaD": 0.13524317875662278,
    "CcSEcCtD": 0.3777723945188029
  },
  "n_trials": 0.0,
  "prediction": 0.00303185614994951,
  "status": 0,
  "training_prediction": 0.00612087156873495
}