{
  "compound_id": "DB00811",
  "compound_name": "Ribavirin",
  "compound_percentile": 0.933823529411765,
  "disease_id": "DOID:9074",
  "disease_name": "systemic lupus erythematosus",
  "disease_percentile": 0.8257477243172952,
  "metapath_contribution": {
    "CbGbCtD": 0.2620622204084835,
    "CbGdCrCtD": 0.002165724171004629,
    "CbGeAlD": 0.03696911325378535,
    "CcSEcCtD": 0.10451512218587726,
    "CiPCiCtD": 0.59161490989705,
    "CrCbGaD": 0.0026729100837992567
  },
  "n_trials": 0.0,
  "prediction": 0.00345296829433851,
  "status": 0
}