{
  "category": "SYM",
  "compound_id": "DB00655",
  "compound_name": "Estrone",
  "compound_percentile": 0.9852941176470591,
  "disease_id": "DOID:1612",
  "disease_name": "breast cancer",
  "disease_percentile": 0.97074122236671,
  "metapath_contribution": {
    "CbGaD": 0.1987442413357594,
    "CbGbCtD": 0.229289440033181,
    "CbGeAlD": 0.011696477960192688,
    "CbGpPWpGaD": 0.04132726779065803,
    "CcSEcCtD": 0.04708435981174518,
    "CrCbGaD": 0.00176432513426886,
    "CrCrCtD": 0.17959814055272438,
    "CrCtD": 0.29049574738147044
  },
  "prediction": 0.0236166633568103,
  "status": 0,
  "training_prediction": 0.118377874118774
}