{
  "compound_id": "DB00818",
  "compound_name": "Propofol",
  "compound_percentile": 0.426470588235294,
  "disease_id": "DOID:9744",
  "disease_name": "type 1 diabetes mellitus",
  "disease_percentile": 0.818595578673602,
  "metapath_contribution": {
    "CbGaD": 0.7549081627162705,
    "CbGpPWpGaD": 0.12211031403595574,
    "CcSEcCtD": 0.11660873772102955,
    "CrCbGaD": 0.0063727855267442755
  },
  "n_trials": 0.0,
  "prediction": 0.00210730105067879,
  "status": 0,
  "training_prediction": 0.000950364471033484
}