{
  "compound_id": "DB04868",
  "compound_name": "Nilotinib",
  "compound_percentile": 0.308823529411765,
  "disease_id": "DOID:7147",
  "disease_name": "ankylosing spondylitis",
  "disease_percentile": 0.11833550065019502,
  "metapath_contribution": {
    "CbGbCtD": 0.45345959423096843,
    "CbGdCrCtD": 0.008175282528437858,
    "CbGeAlD": 0.02550117676932741,
    "CbGpPWpGaD": 0.17635352399845036,
    "CcSEcCtD": 0.33651042247281593
  },
  "n_trials": 0.0,
  "prediction": 0.000990910233292518,
  "status": 0,
  "training_prediction": 0.0020004758808477
}