{
  "compound_id": "DB01016",
  "compound_name": "Glyburide",
  "compound_percentile": 0.647058823529412,
  "disease_id": "DOID:11476",
  "disease_name": "osteoporosis",
  "disease_percentile": 0.6170351105331601,
  "metapath_contribution": {
    "CbGbCtD": 0.7457507533328169,
    "CbGpPWpGaD": 0.09027635034925342,
    "CcSEcCtD": 0.16205632594580605,
    "CrCbGaD": 0.0019165703721235122
  },
  "n_trials": 0.0,
  "prediction": 0.0021764441450536397,
  "status": 0,
  "training_prediction": 0.0117334176813087
}