{
  "compound_id": "DB06689",
  "compound_name": "Ethanolamine Oleate",
  "compound_percentile": 0.838235294117647,
  "disease_id": "DOID:3083",
  "disease_name": "chronic obstructive pulmonary disease",
  "disease_percentile": 0.269180754226268,
  "metapath_contribution": {
    "CbGbCtD": 0.2748732801638727,
    "CbGeAlD": 0.25572720268287497,
    "CbGpPWpGaD": 0.4582303762103072,
    "CcSEcCtD": 0.006741676784365634,
    "CrCbGaD": 0.004427464158579548
  },
  "n_trials": 0.0,
  "prediction": 0.00152988748747354,
  "status": 0
}