{
  "compound_id": "DB00276",
  "compound_name": "Amsacrine",
  "compound_percentile": 0.772058823529412,
  "disease_id": "DOID:1319",
  "disease_name": "brain cancer",
  "disease_percentile": 0.9141742522756829,
  "metapath_contribution": {
    "CbGbCtD": 0.5608417096302014,
    "CbGdCrCtD": 0.0047374076048416185,
    "CbGeAlD": 0.05616212654340857,
    "CbGpPWpGaD": 0.10213421218929025,
    "CcSEcCtD": 0.2761245440322581
  },
  "n_trials": 0.0,
  "prediction": 0.0034372950895419896,
  "status": 0
}