{
  "compound_id": "DB08881",
  "compound_name": "Vemurafenib",
  "compound_percentile": 0.727941176470588,
  "disease_id": "DOID:3083",
  "disease_name": "chronic obstructive pulmonary disease",
  "disease_percentile": 0.611833550065019,
  "metapath_contribution": {
    "CbGaD": 0.510089773157787,
    "CbGbCtD": 0.29467722707141336,
    "CbGeAlD": 0.0027971251146926604,
    "CbGpPWpGaD": 0.08135045064479879,
    "CcSEcCtD": 0.10867679863276968,
    "CrCbGaD": 0.0024086253785383306
  },
  "n_trials": 0.0,
  "prediction": 0.0025261312314259,
  "status": 0,
  "training_prediction": 0.00923267703170879
}