{
  "compound_id": "DB00321",
  "compound_name": "Amitriptyline",
  "compound_percentile": 0.580882352941177,
  "disease_id": "DOID:418",
  "disease_name": "systemic scleroderma",
  "disease_percentile": 0.363459037711313,
  "metapath_contribution": {
    "CbGbCtD": 0.6166628102701582,
    "CbGeAlD": 0.10134290337252953,
    "CbGpPWpGaD": 0.01303170246461261,
    "CcSEcCtD": 0.2689625838926996
  },
  "n_trials": 0.0,
  "prediction": 0.0014266283476239302,
  "status": 0,
  "training_prediction": 0.00340033855561163
}