{
  "compound_id": "DB00349",
  "compound_name": "Clobazam",
  "compound_percentile": 0.647058823529412,
  "disease_id": "DOID:2394",
  "disease_name": "ovarian cancer",
  "disease_percentile": 0.267230169050715,
  "metapath_contribution": {
    "CbGaD": 0.44553271265742844,
    "CbGbCtD": 0.31777583080321414,
    "CbGpPWpGaD": 0.044626517323990596,
    "CcSEcCtD": 0.19160891219122195,
    "CrCbGaD": 0.00045602702414498974
  },
  "n_trials": 0.0,
  "prediction": 0.00105009071549616,
  "status": 0,
  "training_prediction": 0.00250417542525992
}