{
  "compound_id": "DB00513",
  "compound_name": "Aminocaproic Acid",
  "compound_percentile": 0.9852941176470591,
  "disease_id": "DOID:1826",
  "disease_name": "epilepsy syndrome",
  "disease_percentile": 0.583875162548765,
  "metapath_contribution": {
    "CbGaD": 0.5252519233113195,
    "CbGbCtD": 0.20005363809795843,
    "CbGeAlD": 0.009362246018798795,
    "CbGpPWpGaD": 0.1141941714952632,
    "CcSEcCtD": 0.14763257656175718,
    "CrCbGaD": 0.0035054445149029227
  },
  "n_trials": 0.0,
  "prediction": 0.00412159845759055,
  "status": 0
}