{
  "compound_id": "DB08881",
  "compound_name": "Vemurafenib",
  "compound_percentile": 0.580882352941177,
  "disease_id": "DOID:8577",
  "disease_name": "ulcerative colitis",
  "disease_percentile": 0.401820546163849,
  "metapath_contribution": {
    "CbGaD": 0.3124320162377009,
    "CbGbCtD": 0.4292812358809334,
    "CbGeAlD": 0.015910198565881266,
    "CbGpPWpGaD": 0.1175113086976063,
    "CcSEcCtD": 0.1233175816019554,
    "CrCbGaD": 0.0015476590159227749
  },
  "n_trials": 0.0,
  "prediction": 0.00183800886470218,
  "status": 0,
  "training_prediction": 0.0104325674666649
}