{
  "compound_id": "DB00373",
  "compound_name": "Timolol",
  "compound_percentile": 0.713235294117647,
  "disease_id": "DOID:9744",
  "disease_name": "type 1 diabetes mellitus",
  "disease_percentile": 0.9096228868660601,
  "metapath_contribution": {
    "CbGaD": 0.8368157285711858,
    "CbGpPWpGaD": 0.033798952517529145,
    "CcSEcCtD": 0.1219822283210172,
    "CrCbGaD": 0.007403090590267884
  },
  "n_trials": 0.0,
  "prediction": 0.00249904413554895,
  "status": 0,
  "training_prediction": 0.00319826681513527
}