{
  "compound_id": "DB01327",
  "compound_name": "Cefazolin",
  "compound_percentile": 0.992647058823529,
  "disease_id": "DOID:10763",
  "disease_name": "hypertension",
  "disease_percentile": 0.594928478543563,
  "metapath_contribution": {
    "CbGaD": 0.36463384932900944,
    "CbGbCtD": 0.39752028341405976,
    "CbGeAlD": 0.0367734914927703,
    "CbGpPWpGaD": 0.059876312680965875,
    "CcSEcCtD": 0.14039863256709306,
    "CrCbGaD": 0.0007974305161016681
  },
  "n_trials": 0.0,
  "prediction": 0.00489056881151992,
  "status": 0
}