{
  "category": "DM",
  "compound_id": "DB00741",
  "compound_name": "Hydrocortisone",
  "compound_percentile": 0.941176470588235,
  "disease_id": "DOID:13189",
  "disease_name": "gout",
  "disease_percentile": 0.9908972691807539,
  "metapath_contribution": {
    "CbGaD": 0.09791864061379464,
    "CbGbCtD": 0.10670604644150015,
    "CbGpPWpGaD": 0.003060750863512543,
    "CcSEcCtD": 0.04559734650434801,
    "CiPCiCtD": 0.2660241053260131,
    "CrCrCtD": 0.1356081733264114,
    "CrCtD": 0.1879991753114281,
    "CtDrD": 0.1570857616129921
  },
  "prediction": 0.12078996110717699,
  "status": 1,
  "training_prediction": 0.606395417186476
}