{
  "compound_id": "DB00981",
  "compound_name": "Physostigmine",
  "compound_percentile": 0.897058823529412,
  "disease_id": "DOID:9970",
  "disease_name": "obesity",
  "disease_percentile": 0.7002600780234071,
  "metapath_contribution": {
    "CbGaD": 0.7792819769175282,
    "CbGeAlD": 0.02547406820297457,
    "CbGpPWpGaD": 0.17494066211702505,
    "CcSEcCtD": 0.02030329276247202
  },
  "n_trials": 0.0,
  "prediction": 0.00382611834198976,
  "status": 0,
  "training_prediction": 0.00977067208522795
}