{
  "category": "DM",
  "compound_id": "DB00993",
  "compound_name": "Azathioprine",
  "compound_percentile": 0.977941176470588,
  "disease_id": "DOID:8577",
  "disease_name": "ulcerative colitis",
  "disease_percentile": 0.970091027308192,
  "metapath_contribution": {
    "CbGbCtD": 0.3099535237399156,
    "CbGdCrCtD": 0.0013278451769281766,
    "CbGeAlD": 0.010753941904238853,
    "CbGpPWpGaD": 0.0011581473264451745,
    "CcSEcCtD": 0.04831718261535797,
    "CrCrCtD": 0.300119201997794,
    "CtDrD": 0.32837015723932034
  },
  "prediction": 0.0219246544942971,
  "status": 1,
  "training_prediction": 0.234147973098558
}