{
  "compound_id": "DB06148",
  "compound_name": "Mianserin",
  "compound_percentile": 0.8308823529411771,
  "disease_id": "DOID:1936",
  "disease_name": "atherosclerosis",
  "disease_percentile": 0.67295188556567,
  "metapath_contribution": {
    "CbGaD": 0.5114554611839839,
    "CbGbCtD": 0.20618720321828146,
    "CbGeAlD": 0.024962417684018634,
    "CbGpPWpGaD": 0.13774782201520003,
    "CcSEcCtD": 0.11235473723305621,
    "CrCbGaD": 0.007292358665459788
  },
  "n_trials": 0.0,
  "prediction": 0.00232330405478716,
  "status": 0
}