{
  "compound_id": "DB00480",
  "compound_name": "Lenalidomide",
  "compound_percentile": 0.845588235294118,
  "disease_id": "DOID:5408",
  "disease_name": "Paget's disease of bone",
  "disease_percentile": 0.977243172951886,
  "metapath_contribution": {
    "CbGbCtD": 0.4483276210940067,
    "CbGeAlD": 0.029238786131918316,
    "CbGpPWpGaD": 0.20491107567861438,
    "CcSEcCtD": 0.3175225170954607
  },
  "n_trials": 0.0,
  "prediction": 0.0033825586704603603,
  "status": 0,
  "training_prediction": 0.00551072308096693
}