{
  "compound_id": "DB00345",
  "compound_name": "Aminohippurate",
  "compound_percentile": 0.75,
  "disease_id": "DOID:1192",
  "disease_name": "peripheral nervous system neoplasm",
  "disease_percentile": 0.6807542262678801,
  "metapath_contribution": {
    "CbGaD": 0.3063632107980374,
    "CbGbCtD": 0.6239129151034355,
    "CbGpPWpGaD": 0.009248160413754453,
    "CcSEcCtD": 0.057963891310314694,
    "CrCbGaD": 0.002511822374457867
  },
  "n_trials": 0.0,
  "prediction": 0.00219550488555241,
  "status": 0
}