{
  "compound_id": "DB00977",
  "compound_name": "Ethinyl Estradiol",
  "compound_percentile": 0.5367647058823529,
  "disease_id": "DOID:8778",
  "disease_name": "Crohn's disease",
  "disease_percentile": 0.0695708712613784,
  "metapath_contribution": {
    "CbGbCtD": 0.5183360253600985,
    "CbGeAlD": 0.07495111085851579,
    "CcSEcCtD": 0.08179007593378822,
    "CrCbGaD": 0.0004568307674259744,
    "CrCrCtD": 0.3244659570801715
  },
  "n_trials": 0.0,
  "prediction": 0.000836175170488013,
  "status": 0,
  "training_prediction": 0.0022721042601052603
}