{
  "compound_id": "DB00443",
  "compound_name": "Betamethasone",
  "compound_percentile": 0.139705882352941,
  "disease_id": "DOID:3070",
  "disease_name": "malignant glioma",
  "disease_percentile": 0.0188556566970091,
  "metapath_contribution": {
    "CbGaD": 0.5771863039020652,
    "CbGbCtD": 0.03300035356424271,
    "CbGeAlD": 0.0632544816117154,
    "CbGpPWpGaD": 0.14773207949525696,
    "CcSEcCtD": 0.17875513613883384,
    "CrCbGaD": 7.16452878860395e-05
  },
  "n_trials": 0.0,
  "prediction": 0.000492750655884076,
  "status": 0,
  "training_prediction": 0.00246069024638562
}