{
  "compound_id": "DB00327",
  "compound_name": "Hydromorphone",
  "compound_percentile": 1.0,
  "disease_id": "DOID:0050741",
  "disease_name": "alcohol dependence",
  "disease_percentile": 0.994148244473342,
  "metapath_contribution": {
    "CbGaD": 0.22142450249612525,
    "CbGbCtD": 0.16909683553737495,
    "CbGeAlD": 0.006480430543600322,
    "CbGpPWpGaD": 0.021639705426361747,
    "CcSEcCtD": 0.04813804496905169,
    "CrCbGaD": 0.0024854448704354727,
    "CrCrCtD": 0.209124631756049,
    "CrCtD": 0.32161040440100164
  },
  "n_trials": 0.0,
  "prediction": 0.0768022867891022,
  "status": 0
}