{
  "compound_id": "DB00870",
  "compound_name": "Suprofen",
  "compound_percentile": 0.720588235294118,
  "disease_id": "DOID:10652",
  "disease_name": "Alzheimer's disease",
  "disease_percentile": 0.49024707412223706,
  "metapath_contribution": {
    "CbGaD": 0.8498641226027422,
    "CbGbCtD": 0.07557478068286455,
    "CbGpPWpGaD": 0.05882339353120104,
    "CcSEcCtD": 0.005583753082940488,
    "CrCbGaD": 0.010153950100251611
  },
  "n_trials": 0.0,
  "prediction": 0.0018227077352566,
  "status": 0
}