{
  "compound_id": "DB08877",
  "compound_name": "Ruxolitinib",
  "compound_percentile": 0.897058823529412,
  "disease_id": "DOID:8778",
  "disease_name": "Crohn's disease",
  "disease_percentile": 0.8920676202860859,
  "metapath_contribution": {
    "CbGaD": 0.7205025952565526,
    "CbGeAlD": 0.08607540577499806,
    "CbGpPWpGaD": 0.16370967945455933,
    "CcSEcCtD": 0.02971231951389007
  },
  "n_trials": 0.0,
  "prediction": 0.00343961150551198,
  "status": 0,
  "training_prediction": 0.005603469352458671
}