{
  "compound_id": "DB00788",
  "compound_name": "Naproxen",
  "compound_percentile": 0.44117647058823495,
  "disease_id": "DOID:14221",
  "disease_name": "metabolic syndrome X",
  "disease_percentile": 0.4128738621586479,
  "metapath_contribution": {
    "CbGaD": 0.7176625724683269,
    "CbGeAlD": 0.021442015616217922,
    "CbGpPWpGaD": 0.1610261457764504,
    "CcSEcCtD": 0.0890689445691466,
    "CrCbGaD": 0.010800321569858141
  },
  "n_trials": 0.0,
  "prediction": 0.00123838497940346,
  "status": 0,
  "training_prediction": 0.0005582281299719701
}