{
  "compound_id": "DB00831",
  "compound_name": "Trifluoperazine",
  "compound_percentile": 0.360294117647059,
  "disease_id": "DOID:4045",
  "disease_name": "muscle cancer",
  "disease_percentile": 0.0806241872561769,
  "metapath_contribution": {
    "CbGbCtD": 0.5357067531790081,
    "CbGeAlD": 0.17370194557987936,
    "CbGpPWpGaD": 0.18968747395485958,
    "CcSEcCtD": 0.10033331691538783,
    "CrCbGaD": 0.000570510370865246
  },
  "n_trials": 0.0,
  "prediction": 0.0007551462459280849,
  "status": 0
}